{"item2": {"segmentation": [[118, 3, 139, 82, 256, 67, 350, 36, 352, 3, 118, 3]], "scale": 1, "viewpoint": 2, "zoom_in": 3, "landmarks": [0, 0, 0, 0, 0, 0, 0, 0, 0, 0, 0, 0, 0, 0, 0, 0, 0, 0, 0, 0, 0, 0, 0, 0, 0, 0, 0, 0, 0, 0, 0, 0, 0, 0, 0, 0, 0, 0, 0, 0, 0, 0, 139, 82, 2, 256, 67, 2, 350, 36, 2, 0, 0, 0, 0, 0, 0, 0, 0, 0, 0, 0, 0, 0, 0, 0, 0, 0, 0, 0, 0, 0, 0, 0, 0], "style": 0, "bounding_box": [105, 1, 386, 90], "category_id": 1, "occlusion": 1, "category_name": "short sleeve top"}, "source": "shop", "pair_id": 26, "item1": {"segmentation": [[358, 9, 234, 19, 121, 25, 125, 201, 134, 361, 124, 465, 209, 468, 205, 361, 258, 148, 317, 342, 325, 428, 411, 424, 390, 334, 384, 179, 358, 9], [234, 19, 121, 25, 125, 201, 134, 361, 124, 465, 209, 468, 205, 361, 258, 148, 234, 19], [358, 9, 234, 19, 258, 148, 317, 342, 325, 428, 411, 424, 390, 334, 384, 179, 358, 9]], "scale": 3, "viewpoint": 2, "zoom_in": 1, "landmarks": [121, 25, 1, 234, 19, 1, 358, 9, 1, 125, 201, 2, 134, 361, 2, 124, 465, 2, 209, 468, 2, 205, 361, 2, 258, 148, 2, 317, 342, 2, 325, 428, 2, 411, 424, 2, 390, 334, 2, 384, 179, 2], "style": 2, "bounding_box": [88, 8, 434, 502], "category_id": 8, "occlusion": 2, "category_name": "trousers"}}