{"item2": {"segmentation": [[132, 410, 224, 421, 301, 424, 312, 559, 307, 660, 180, 690, 24, 611, 74, 514, 132, 410]], "scale": 2, "viewpoint": 2, "zoom_in": 1, "landmarks": [132, 410, 1, 224, 421, 1, 301, 424, 1, 74, 514, 2, 24, 611, 2, 180, 690, 2, 307, 660, 2, 312, 559, 2], "style": 1, "bounding_box": [17, 394, 334, 701], "category_id": 9, "occlusion": 2, "category_name": "skirt"}, "source": "shop", "pair_id": 168, "item1": {"segmentation": [[163, 199, 185, 236, 230, 255, 271, 236, 288, 206, 336, 217, 322, 304, 315, 366, 303, 428, 219, 428, 134, 417, 131, 353, 131, 295, 131, 209, 163, 199]], "scale": 2, "viewpoint": 2, "zoom_in": 1, "landmarks": [233, 206, 1, 163, 199, 1, 185, 236, 1, 230, 255, 2, 271, 236, 2, 288, 206, 2, 131, 209, 1, 131, 295, 1, 131, 353, 1, 0, 0, 0, 0, 0, 0, 0, 0, 0, 315, 366, 2, 322, 304, 2, 336, 217, 2], "style": 0, "bounding_box": [105, 189, 350, 442], "category_id": 5, "occlusion": 2, "category_name": "vest"}}