{"source": "shop", "pair_id": 289, "item1": {"segmentation": [[223, 227, 240, 223, 257, 215, 289, 242, 257, 330, 292, 437, 280, 541, 209, 538, 149, 472, 159, 397, 178, 311, 223, 227]], "scale": 2, "viewpoint": 2, "zoom_in": 1, "landmarks": [0, 0, 0, 0, 0, 0, 0, 0, 0, 223, 227, 2, 240, 223, 2, 257, 215, 2, 0, 0, 0, 178, 311, 1, 159, 397, 2, 149, 472, 1, 209, 538, 2, 280, 541, 2, 292, 437, 1, 257, 330, 2, 289, 242, 2], "style": 1, "bounding_box": [124, 214, 326, 550], "category_id": 5, "occlusion": 2, "category_name": "vest"}}