{"item2": {"segmentation": [[365, 16, 353, 81, 444, 46, 534, 95, 541, 14, 365, 16]], "scale": 1, "viewpoint": 2, "zoom_in": 3, "landmarks": [0, 0, 0, 0, 0, 0, 0, 0, 0, 0, 0, 0, 0, 0, 0, 0, 0, 0, 0, 0, 0, 0, 0, 0, 0, 0, 0, 0, 0, 0, 0, 0, 0, 0, 0, 0, 0, 0, 0, 0, 0, 0, 353, 81, 2, 0, 0, 0, 534, 95, 2, 0, 0, 0, 0, 0, 0, 0, 0, 0, 0, 0, 0, 0, 0, 0, 0, 0, 0, 0, 0, 0, 0, 0, 0], "style": 0, "bounding_box": [344, 12, 546, 100], "category_id": 1, "occlusion": 1, "category_name": "short sleeve top"}, "source": "shop", "pair_id": 479, "item1": {"segmentation": [[525, 42, 444, 47, 361, 41, 346, 114, 350, 184, 438, 217, 437, 183, 446, 213, 541, 196, 530, 120, 525, 42], [444, 47, 361, 41, 346, 114, 350, 184, 438, 217, 437, 183, 444, 47], [525, 42, 444, 47, 437, 183, 446, 213, 541, 196, 530, 120, 525, 42]], "scale": 1, "viewpoint": 2, "zoom_in": 1, "landmarks": [361, 41, 1, 444, 47, 2, 525, 42, 1, 346, 114, 2, 350, 184, 1, 438, 217, 2, 437, 183, 2, 446, 213, 2, 541, 196, 2, 530, 120, 2], "style": 1, "bounding_box": [338, 35, 546, 252], "category_id": 7, "occlusion": 2, "category_name": "shorts"}}