{"source": "user", "pair_id": 523, "item1": {"segmentation": [[3, 3, 2, 93, 5, 195, 34, 276, 80, 450, 163, 603, 281, 599, 380, 563, 384, 415, 396, 239, 402, 150, 405, 52, 415, 11, 439, 27, 461, 52, 464, 3, 3, 3], [415, 11, 439, 27, 461, 52, 464, 3, 415, 11]], "scale": 3, "viewpoint": 2, "zoom_in": 2, "landmarks": [0, 0, 0, 0, 0, 0, 0, 0, 0, 0, 0, 0, 0, 0, 0, 0, 0, 0, 0, 0, 0, 0, 0, 0, 0, 0, 0, 0, 0, 0, 0, 0, 0, 0, 0, 0, 0, 0, 0, 5, 195, 2, 34, 276, 2, 80, 450, 2, 163, 603, 2, 281, 599, 2, 380, 563, 2, 384, 415, 2, 396, 239, 2, 402, 150, 2, 405, 52, 2, 415, 11, 2, 439, 27, 2, 0, 0, 0, 0, 0, 0, 0, 0, 0, 0, 0, 0], "style": 1, "bounding_box": [0, 1, 466, 611], "category_id": 10, "occlusion": 1, "category_name": "short sleeve dress"}}