{"source": "user", "pair_id": 653, "item1": {"segmentation": [[333, 1, 367, 75, 357, 158, 360, 219, 411, 371, 467, 563, 278, 623, 31, 623, 44, 440, 66, 234, 57, 137, 50, 72, 46, 2, 333, 1]], "scale": 3, "viewpoint": 1, "zoom_in": 3, "landmarks": [0, 0, 0, 0, 0, 0, 0, 0, 0, 0, 0, 0, 0, 0, 0, 0, 0, 0, 0, 0, 0, 50, 72, 2, 57, 137, 2, 66, 234, 2, 44, 440, 2, 0, 0, 0, 0, 0, 0, 0, 0, 0, 411, 371, 2, 360, 219, 2, 357, 158, 2, 367, 75, 2, 0, 0, 0], "style": 1, "bounding_box": [22, 7, 467, 623], "category_id": 12, "occlusion": 1, "category_name": "vest dress"}}