{"source": "user", "pair_id": 989, "item1": {"segmentation": [[307, 1, 219, 30, 161, 18, 53, 1, 23, 7, 3, 14, 29, 121, 30, 154, 6, 590, 250, 614, 465, 585, 465, 161, 467, 2, 426, 20, 411, 23, 307, 1], [53, 1, 23, 7, 3, 14, 29, 121, 53, 1], [467, 2, 426, 20, 411, 23, 467, 2], [161, 18, 219, 30, 307, 1, 161, 18]], "scale": 3, "viewpoint": 1, "zoom_in": 3, "landmarks": [0, 0, 0, 0, 0, 0, 161, 18, 2, 219, 30, 2, 0, 0, 0, 0, 0, 0, 0, 0, 0, 23, 7, 2, 0, 0, 0, 0, 0, 0, 0, 0, 0, 29, 121, 2, 30, 154, 2, 0, 0, 0, 0, 0, 0, 250, 614, 2, 0, 0, 0, 0, 0, 0, 0, 0, 0, 0, 0, 0, 0, 0, 0, 0, 0, 0, 0, 0, 0, 426, 20, 2, 411, 23, 2], "style": 2, "bounding_box": [1, 0, 466, 623], "category_id": 1, "occlusion": 1, "category_name": "short sleeve top"}}