{"item2": {"segmentation": [[45, 434, 190, 402, 291, 320, 330, 433, 356, 563, 259, 622, 126, 623, 68, 546, 45, 434]], "scale": 2, "viewpoint": 2, "zoom_in": 2, "landmarks": [45, 434, 1, 190, 402, 1, 291, 320, 1, 68, 546, 2, 0, 0, 0, 0, 0, 0, 356, 563, 2, 330, 433, 2], "style": 2, "bounding_box": [36, 320, 357, 623], "category_id": 9, "occlusion": 2, "category_name": "skirt"}, "source": "user", "pair_id": 1115, "item1": {"segmentation": [[120, 3, 114, 18, 98, 29, 53, 41, 2, 28, 2, 260, 17, 376, 65, 470, 231, 405, 294, 326, 280, 228, 253, 144, 183, 3, 120, 3]], "scale": 3, "viewpoint": 2, "zoom_in": 3, "landmarks": [0, 0, 0, 0, 0, 0, 53, 41, 2, 98, 29, 2, 114, 18, 2, 0, 0, 0, 0, 0, 0, 0, 0, 0, 0, 0, 0, 0, 0, 0, 0, 0, 0, 0, 0, 0, 0, 0, 0, 17, 376, 2, 65, 470, 2, 231, 405, 2, 294, 326, 2, 280, 228, 2, 253, 144, 2, 0, 0, 0, 0, 0, 0, 0, 0, 0, 0, 0, 0, 0, 0, 0, 0, 0, 0], "style": 1, "bounding_box": [1, 0, 294, 473], "category_id": 1, "occlusion": 1, "category_name": "short sleeve top"}}