{"item2": {"segmentation": [[179, 289, 233, 285, 289, 278, 352, 446, 385, 656, 308, 699, 206, 680, 176, 482, 179, 289]], "scale": 2, "viewpoint": 2, "zoom_in": 2, "landmarks": [179, 289, 1, 233, 285, 2, 289, 278, 2, 176, 482, 2, 206, 680, 2, 0, 0, 0, 385, 656, 2, 352, 446, 2], "style": 2, "bounding_box": [157, 276, 386, 701], "category_id": 9, "occlusion": 1, "category_name": "skirt"}, "source": "shop", "pair_id": 1176, "item1": {"segmentation": [[158, 124, 183, 171, 231, 191, 262, 160, 252, 121, 271, 120, 279, 194, 285, 237, 288, 276, 235, 282, 186, 287, 175, 245, 165, 215, 137, 128, 158, 124]], "scale": 1, "viewpoint": 2, "zoom_in": 1, "landmarks": [216, 143, 1, 158, 124, 1, 183, 171, 2, 231, 191, 2, 262, 160, 2, 252, 121, 1, 137, 128, 1, 165, 215, 2, 175, 245, 2, 0, 0, 0, 0, 0, 0, 0, 0, 0, 285, 237, 2, 279, 194, 2, 271, 120, 1], "style": 1, "bounding_box": [132, 116, 290, 290], "category_id": 5, "occlusion": 2, "category_name": "vest"}}