{"item2": {"segmentation": [[85, 510, 250, 509, 400, 509, 402, 571, 399, 621, 247, 623, 86, 622, 77, 574, 85, 510]], "scale": 2, "viewpoint": 2, "zoom_in": 3, "landmarks": [85, 510, 1, 250, 509, 1, 400, 509, 1, 77, 574, 2, 0, 0, 0, 0, 0, 0, 0, 0, 0, 402, 571, 2], "style": 0, "bounding_box": [74, 508, 405, 623], "category_id": 9, "occlusion": 2, "category_name": "skirt"}, "source": "user", "pair_id": 1360, "item1": {"segmentation": [[148, 1, 173, 8, 214, 8, 258, 5, 280, 0, 314, 28, 385, 157, 394, 342, 407, 530, 255, 571, 63, 551, 69, 361, 66, 156, 131, 28, 148, 1]], "scale": 3, "viewpoint": 2, "zoom_in": 2, "landmarks": [0, 0, 0, 0, 0, 0, 173, 8, 2, 214, 8, 2, 258, 5, 2, 0, 0, 0, 131, 28, 2, 66, 156, 2, 69, 361, 2, 63, 551, 2, 255, 571, 2, 407, 530, 2, 394, 342, 2, 385, 157, 2, 314, 28, 2], "style": 1, "bounding_box": [59, 0, 411, 595], "category_id": 5, "occlusion": 1, "category_name": "vest"}}