{"source": "user", "pair_id": 1449, "item1": {"segmentation": [[211, 2, 223, 5, 271, 3, 254, 54, 249, 71, 237, 98, 235, 132, 223, 190, 187, 191, 149, 176, 157, 121, 169, 89, 171, 62, 173, 41, 179, 2, 211, 2]], "scale": 2, "viewpoint": 2, "zoom_in": 2, "landmarks": [0, 0, 0, 0, 0, 0, 0, 0, 0, 223, 5, 2, 0, 0, 0, 0, 0, 0, 0, 0, 0, 173, 41, 2, 171, 62, 2, 169, 89, 2, 157, 121, 2, 149, 176, 2, 187, 191, 2, 223, 190, 1, 235, 132, 2, 237, 98, 2, 249, 71, 2, 254, 54, 2, 271, 3, 2], "style": 1, "bounding_box": [143, 1, 274, 195], "category_id": 12, "occlusion": 1, "category_name": "vest dress"}}