{"item2": {"segmentation": [[283, 188, 348, 211, 402, 227, 388, 304, 360, 363, 266, 380, 206, 345, 237, 265, 283, 188]], "scale": 2, "viewpoint": 2, "zoom_in": 1, "landmarks": [283, 188, 1, 348, 211, 1, 402, 227, 1, 237, 265, 1, 206, 345, 2, 266, 380, 2, 360, 363, 2, 388, 304, 2], "style": 0, "bounding_box": [203, 180, 404, 388], "category_id": 9, "occlusion": 2, "category_name": "skirt"}, "source": "shop", "pair_id": 1796, "item1": {"segmentation": [[395, 12, 391, 31, 406, 45, 437, 46, 466, 37, 519, 100, 462, 140, 425, 194, 402, 250, 341, 222, 281, 197, 293, 137, 300, 82, 305, 28, 395, 12]], "scale": 2, "viewpoint": 2, "zoom_in": 1, "landmarks": [423, 25, 1, 395, 12, 2, 391, 31, 2, 406, 45, 1, 437, 46, 1, 466, 37, 1, 305, 28, 2, 300, 82, 2, 293, 137, 1, 0, 0, 0, 0, 0, 0, 0, 0, 0, 425, 194, 1, 462, 140, 2, 519, 100, 2], "style": 1, "bounding_box": [280, 9, 523, 254], "category_id": 5, "occlusion": 2, "category_name": "vest"}}