{"source": "user", "pair_id": 1846, "item1": {"segmentation": [[207, 2, 218, 40, 235, 86, 299, 219, 299, 369, 177, 399, 2, 399, 1, 253, 24, 108, 18, 53, 1, 1, 207, 2]], "scale": 3, "viewpoint": 1, "zoom_in": 3, "landmarks": [0, 0, 0, 0, 0, 0, 0, 0, 0, 0, 0, 0, 0, 0, 0, 0, 0, 0, 0, 0, 0, 0, 0, 0, 18, 53, 2, 24, 108, 2, 0, 0, 0, 0, 0, 0, 0, 0, 0, 0, 0, 0, 0, 0, 0, 235, 86, 2, 218, 40, 2, 0, 0, 0, 0, 0, 0], "style": 1, "bounding_box": [0, 0, 299, 399], "category_id": 12, "occlusion": 1, "category_name": "vest dress"}}