{"source": "user", "pair_id": 2062, "item1": {"segmentation": [[340, 2, 345, 48, 351, 166, 353, 308, 154, 323, 2, 172, 104, 89, 154, 16, 164, 1, 340, 2]], "scale": 3, "viewpoint": 2, "zoom_in": 3, "landmarks": [0, 0, 0, 0, 0, 0, 0, 0, 0, 0, 0, 0, 0, 0, 0, 0, 0, 0, 0, 0, 0, 0, 0, 0, 0, 0, 0, 154, 16, 2, 104, 89, 2, 0, 0, 0, 0, 0, 0, 0, 0, 0, 0, 0, 0, 345, 48, 2, 0, 0, 0, 0, 0, 0, 0, 0, 0], "style": 1, "bounding_box": [1, 0, 353, 324], "category_id": 12, "occlusion": 1, "category_name": "vest dress"}}