{"source": "user", "pair_id": 2587, "item1": {"segmentation": [[51, 361, 76, 475, 191, 566, 323, 485, 365, 365, 391, 365, 349, 686, 358, 828, 24, 831, 15, 693, 4, 364, 51, 361]], "scale": 3, "viewpoint": 2, "zoom_in": 2, "landmarks": [187, 524, 1, 51, 361, 1, 76, 475, 1, 191, 566, 2, 323, 485, 1, 365, 365, 1, 4, 364, 1, 15, 693, 1, 0, 0, 0, 0, 0, 0, 0, 0, 0, 0, 0, 0, 0, 0, 0, 0, 0, 0, 0, 0, 0, 0, 0, 0, 0, 0, 0, 349, 686, 1, 391, 365, 1], "style": 1, "bounding_box": [0, 323, 398, 831], "category_id": 12, "occlusion": 3, "category_name": "vest dress"}}