{"item2": {"segmentation": [[174, 4, 188, 98, 165, 181, 330, 187, 457, 174, 499, 81, 513, 6, 174, 4]], "scale": 2, "viewpoint": 2, "zoom_in": 2, "landmarks": [0, 0, 0, 0, 0, 0, 0, 0, 0, 0, 0, 0, 0, 0, 0, 0, 0, 0, 0, 0, 0, 0, 0, 0, 0, 0, 0, 0, 0, 0, 0, 0, 0, 0, 0, 0, 0, 0, 0, 188, 98, 2, 0, 0, 0, 0, 0, 0, 0, 0, 0, 499, 81, 2, 0, 0, 0, 0, 0, 0, 0, 0, 0, 0, 0, 0, 0, 0, 0, 0, 0, 0, 0, 0, 0], "style": 0, "bounding_box": [134, 3, 518, 201], "category_id": 1, "occlusion": 1, "category_name": "short sleeve top"}, "source": "shop", "pair_id": 2838, "item1": {"segmentation": [[456, 174, 325, 191, 178, 172, 111, 351, 78, 541, 318, 578, 325, 525, 321, 585, 567, 535, 522, 346, 456, 174], [325, 191, 178, 172, 111, 351, 78, 541, 318, 578, 325, 525, 325, 191], [456, 174, 325, 191, 325, 525, 321, 585, 567, 535, 522, 346, 456, 174]], "scale": 2, "viewpoint": 2, "zoom_in": 1, "landmarks": [178, 172, 1, 325, 191, 2, 456, 174, 1, 111, 351, 2, 78, 541, 2, 318, 578, 1, 325, 525, 2, 321, 585, 2, 567, 535, 2, 522, 346, 2], "style": 1, "bounding_box": [53, 148, 570, 602], "category_id": 7, "occlusion": 2, "category_name": "shorts"}}