{"item2": {"segmentation": [[81, 769, 274, 885, 468, 792, 478, 884, 482, 957, 4, 958, 25, 873, 81, 769]], "scale": 2, "viewpoint": 2, "zoom_in": 2, "landmarks": [81, 769, 1, 274, 885, 1, 468, 792, 2, 25, 873, 2, 0, 0, 0, 0, 0, 0, 0, 0, 0, 478, 884, 2], "style": 0, "bounding_box": [1, 743, 484, 959], "category_id": 9, "occlusion": 2, "category_name": "skirt"}, "source": "shop", "pair_id": 3038, "item1": {"segmentation": [[290, 58, 333, 121, 409, 147, 467, 140, 500, 109, 573, 130, 560, 398, 510, 552, 474, 708, 314, 707, 114, 676, 130, 507, 126, 346, 172, 77, 290, 58]], "scale": 3, "viewpoint": 2, "zoom_in": 1, "landmarks": [395, 92, 1, 290, 58, 2, 333, 121, 2, 409, 147, 2, 467, 140, 1, 500, 109, 1, 172, 77, 2, 126, 346, 2, 130, 507, 2, 114, 676, 1, 314, 707, 2, 474, 708, 2, 510, 552, 2, 560, 398, 1, 573, 130, 1], "style": 1, "bounding_box": [103, 54, 583, 723], "category_id": 5, "occlusion": 2, "category_name": "vest"}}