{"item2": {"segmentation": [[236, 499, 326, 507, 408, 503, 433, 639, 206, 638, 236, 499]], "scale": 1, "viewpoint": 2, "zoom_in": 3, "landmarks": [236, 499, 1, 326, 507, 1, 408, 503, 1, 0, 0, 0, 0, 0, 0, 0, 0, 0, 0, 0, 0, 0, 0, 0], "style": 0, "bounding_box": [195, 494, 455, 639], "category_id": 9, "occlusion": 3, "category_name": "skirt"}, "source": "shop", "pair_id": 3148, "item1": {"segmentation": [[300, 269, 317, 306, 347, 322, 379, 306, 393, 273, 438, 289, 430, 363, 430, 438, 430, 530, 314, 512, 192, 536, 216, 436, 243, 354, 257, 266, 300, 269]], "scale": 2, "viewpoint": 2, "zoom_in": 1, "landmarks": [347, 278, 1, 300, 269, 2, 317, 306, 2, 347, 322, 2, 379, 306, 1, 393, 273, 1, 257, 266, 2, 243, 354, 2, 216, 436, 2, 192, 536, 2, 0, 0, 0, 430, 530, 1, 430, 438, 1, 430, 363, 1, 438, 289, 2], "style": 2, "bounding_box": [179, 263, 452, 548], "category_id": 5, "occlusion": 2, "category_name": "vest"}}