{"item2": {"segmentation": [[384, 86, 294, 109, 208, 94, 173, 210, 157, 269, 296, 328, 293, 250, 304, 321, 437, 255, 420, 181, 384, 86], [294, 109, 208, 94, 173, 210, 157, 269, 296, 328, 293, 250, 294, 109], [384, 86, 294, 109, 293, 250, 304, 321, 437, 255, 420, 181, 384, 86]], "scale": 2, "viewpoint": 2, "zoom_in": 1, "landmarks": [208, 94, 1, 294, 109, 1, 384, 86, 1, 173, 210, 2, 157, 269, 2, 296, 328, 2, 293, 250, 2, 304, 321, 2, 437, 255, 2, 420, 181, 2], "style": 1, "bounding_box": [154, 79, 441, 346], "category_id": 7, "occlusion": 2, "category_name": "shorts"}, "source": "user", "pair_id": 3159, "item1": {"segmentation": [[198, 2, 200, 110, 306, 118, 394, 81, 387, 1, 198, 2]], "scale": 1, "viewpoint": 2, "zoom_in": 3, "landmarks": [0, 0, 0, 0, 0, 0, 0, 0, 0, 0, 0, 0, 0, 0, 0, 0, 0, 0, 0, 0, 0, 0, 0, 0, 0, 0, 0, 0, 0, 0, 0, 0, 0, 0, 0, 0, 0, 0, 0, 0, 0, 0, 200, 110, 1, 306, 118, 2, 394, 81, 2, 0, 0, 0, 0, 0, 0, 0, 0, 0, 0, 0, 0, 0, 0, 0, 0, 0, 0, 0, 0, 0, 0, 0, 0], "style": 0, "bounding_box": [193, 0, 401, 127], "category_id": 1, "occlusion": 1, "category_name": "short sleeve top"}}