{"source": "user", "pair_id": 3816, "item1": {"segmentation": [[129, 1, 1, 121, 5, 337, 41, 309, 53, 279, 50, 316, 78, 416, 111, 587, 324, 620, 458, 553, 467, 333, 465, 179, 465, 4, 129, 1], [1, 121, 5, 337, 41, 309, 53, 279, 1, 121]], "scale": 3, "viewpoint": 1, "zoom_in": 3, "landmarks": [0, 0, 0, 0, 0, 0, 0, 0, 0, 0, 0, 0, 0, 0, 0, 0, 0, 0, 0, 0, 0, 0, 0, 0, 0, 0, 0, 5, 337, 2, 41, 309, 2, 53, 279, 2, 50, 316, 2, 78, 416, 2, 111, 587, 2, 0, 0, 0, 458, 553, 2, 0, 0, 0, 0, 0, 0, 0, 0, 0, 0, 0, 0, 0, 0, 0, 0, 0, 0, 0, 0, 0, 0, 0, 0], "style": 2, "bounding_box": [0, 0, 465, 623], "category_id": 1, "occlusion": 1, "category_name": "short sleeve top"}}