{"item2": {"segmentation": [[33, 429, 218, 438, 359, 384, 387, 577, 458, 753, 255, 830, 22, 827, 33, 625, 33, 429]], "scale": 3, "viewpoint": 2, "zoom_in": 2, "landmarks": [33, 429, 2, 218, 438, 2, 359, 384, 2, 33, 625, 2, 0, 0, 0, 0, 0, 0, 458, 753, 2, 387, 577, 2], "style": 2, "bounding_box": [1, 363, 466, 831], "category_id": 9, "occlusion": 1, "category_name": "skirt"}, "source": "user", "pair_id": 4008, "item1": {"segmentation": [[3, 5, 1, 271, 15, 353, 40, 424, 217, 438, 352, 383, 384, 257, 383, 113, 384, 70, 394, 138, 417, 221, 466, 169, 466, 73, 391, 1, 3, 5], [384, 70, 394, 138, 417, 221, 466, 169, 466, 73, 391, 1, 384, 70]], "scale": 3, "viewpoint": 2, "zoom_in": 3, "landmarks": [0, 0, 0, 0, 0, 0, 0, 0, 0, 0, 0, 0, 0, 0, 0, 0, 0, 0, 0, 0, 0, 0, 0, 0, 0, 0, 0, 0, 0, 0, 0, 0, 0, 0, 0, 0, 0, 0, 0, 15, 353, 2, 0, 0, 0, 0, 0, 0, 0, 0, 0, 384, 257, 2, 383, 113, 2, 384, 70, 2, 394, 138, 2, 417, 221, 2, 0, 0, 0, 0, 0, 0, 0, 0, 0], "style": 1, "bounding_box": [0, 1, 466, 472], "category_id": 1, "occlusion": 1, "category_name": "short sleeve top"}}