{"item2": {"segmentation": [[7, 2, 67, 26, 70, 2, 76, 2, 68, 79, 71, 146, 230, 165, 399, 148, 408, 68, 400, 2, 412, 21, 422, 32, 438, 2, 7, 2], [7, 2, 67, 26, 70, 2, 7, 2], [412, 21, 422, 32, 438, 2, 412, 21]], "scale": 2, "viewpoint": 2, "zoom_in": 3, "landmarks": [0, 0, 0, 0, 0, 0, 0, 0, 0, 0, 0, 0, 0, 0, 0, 0, 0, 0, 0, 0, 0, 0, 0, 0, 0, 0, 0, 67, 26, 2, 0, 0, 0, 0, 0, 0, 0, 0, 0, 68, 79, 2, 0, 0, 0, 0, 0, 0, 0, 0, 0, 408, 68, 2, 0, 0, 0, 0, 0, 0, 412, 21, 2, 422, 32, 2, 0, 0, 0, 0, 0, 0, 0, 0, 0], "style": 0, "bounding_box": [0, 0, 467, 177], "category_id": 1, "occlusion": 1, "category_name": "short sleeve top"}, "source": "shop", "pair_id": 4194, "item1": {"segmentation": [[395, 150, 239, 167, 78, 152, 34, 315, 22, 485, 228, 533, 232, 498, 244, 542, 456, 509, 432, 322, 395, 150], [239, 167, 78, 152, 34, 315, 22, 485, 228, 533, 232, 498, 239, 167], [395, 150, 239, 167, 232, 498, 244, 542, 456, 509, 432, 322, 395, 150]], "scale": 3, "viewpoint": 2, "zoom_in": 1, "landmarks": [78, 152, 2, 239, 167, 2, 395, 150, 2, 34, 315, 2, 22, 485, 1, 228, 533, 2, 232, 498, 2, 244, 542, 2, 456, 509, 2, 432, 322, 2], "style": 1, "bounding_box": [16, 141, 467, 566], "category_id": 7, "occlusion": 1, "category_name": "shorts"}}