{"source": "user", "pair_id": 4304, "item1": {"segmentation": [[397, 50, 359, 128, 271, 193, 170, 177, 136, 94, 4, 161, 1, 461, 35, 484, 40, 445, 47, 412, 68, 450, 90, 561, 26, 707, 151, 828, 464, 828, 464, 58, 397, 50], [4, 161, 1, 461, 35, 484, 40, 445, 47, 412, 4, 161]], "scale": 3, "viewpoint": 2, "zoom_in": 2, "landmarks": [247, 86, 1, 136, 94, 2, 170, 177, 2, 271, 193, 2, 359, 128, 2, 397, 50, 2, 0, 0, 0, 0, 0, 0, 0, 0, 0, 35, 484, 2, 40, 445, 2, 47, 412, 2, 68, 450, 2, 90, 561, 2, 26, 707, 2, 0, 0, 0, 0, 0, 0, 0, 0, 0, 0, 0, 0, 0, 0, 0, 0, 0, 0, 0, 0, 0, 0, 0, 0, 0, 0, 0, 0, 0, 0], "style": 1, "bounding_box": [0, 32, 465, 831], "category_id": 1, "occlusion": 1, "category_name": "short sleeve top"}}