{"item2": {"segmentation": [[233, 47, 288, 25, 334, 50, 332, 123, 354, 208, 251, 227, 223, 181, 303, 227, 223, 237, 206, 130, 233, 47], [288, 25, 334, 50, 332, 123, 354, 208, 251, 227, 223, 181, 288, 25], [233, 47, 288, 25, 223, 181, 303, 227, 223, 237, 206, 130, 233, 47]], "scale": 1, "viewpoint": 3, "zoom_in": 1, "landmarks": [334, 50, 2, 288, 25, 2, 233, 47, 2, 332, 123, 2, 354, 208, 2, 251, 227, 2, 223, 181, 2, 303, 227, 1, 223, 237, 2, 206, 130, 2], "style": 1, "bounding_box": [203, 22, 355, 240], "category_id": 7, "occlusion": 1, "category_name": "shorts"}, "source": "shop", "pair_id": 4390, "item1": {"segmentation": [[203, 5, 231, 57, 282, 24, 334, 52, 339, 3, 203, 5]], "scale": 1, "viewpoint": 2, "zoom_in": 3, "landmarks": [0, 0, 0, 0, 0, 0, 0, 0, 0, 0, 0, 0, 0, 0, 0, 0, 0, 0, 0, 0, 0, 0, 0, 0, 0, 0, 0, 0, 0, 0, 0, 0, 0, 0, 0, 0, 0, 0, 0, 0, 0, 0, 0, 0, 0, 0, 0, 0, 0, 0, 0, 0, 0, 0, 0, 0, 0, 0, 0, 0, 0, 0, 0, 0, 0, 0, 0, 0, 0, 0, 0, 0, 0, 0, 0], "style": 0, "bounding_box": [199, 1, 341, 61], "category_id": 1, "occlusion": 1, "category_name": "short sleeve top"}}