{"item2": {"segmentation": [[490, 10, 435, 14, 385, 41, 388, 117, 368, 199, 429, 201, 423, 173, 429, 214, 524, 205, 525, 90, 490, 10], [435, 14, 385, 41, 388, 117, 368, 199, 429, 201, 423, 173, 435, 14], [490, 10, 435, 14, 423, 173, 429, 214, 524, 205, 525, 90, 490, 10]], "scale": 1, "viewpoint": 2, "zoom_in": 1, "landmarks": [385, 41, 2, 435, 14, 2, 490, 10, 2, 388, 117, 2, 368, 199, 2, 429, 201, 2, 423, 173, 2, 429, 214, 2, 524, 205, 2, 525, 90, 2], "style": 1, "bounding_box": [367, 5, 533, 216], "category_id": 7, "occlusion": 1, "category_name": "shorts"}, "source": "shop", "pair_id": 4390, "item1": {"segmentation": [[381, 6, 388, 34, 437, 12, 494, 28, 514, 5, 381, 6]], "scale": 1, "viewpoint": 2, "zoom_in": 3, "landmarks": [0, 0, 0, 0, 0, 0, 0, 0, 0, 0, 0, 0, 0, 0, 0, 0, 0, 0, 0, 0, 0, 0, 0, 0, 0, 0, 0, 0, 0, 0, 0, 0, 0, 0, 0, 0, 0, 0, 0, 0, 0, 0, 0, 0, 0, 0, 0, 0, 0, 0, 0, 0, 0, 0, 0, 0, 0, 0, 0, 0, 0, 0, 0, 0, 0, 0, 0, 0, 0, 0, 0, 0, 0, 0, 0], "style": 0, "bounding_box": [377, 5, 517, 37], "category_id": 1, "occlusion": 1, "category_name": "short sleeve top"}}