{"item2": {"segmentation": [[166, 12, 163, 116, 351, 103, 553, 80, 599, 14, 166, 12]], "scale": 2, "viewpoint": 2, "zoom_in": 3, "landmarks": [0, 0, 0, 0, 0, 0, 0, 0, 0, 0, 0, 0, 0, 0, 0, 0, 0, 0, 0, 0, 0, 0, 0, 0, 0, 0, 0, 0, 0, 0, 0, 0, 0, 0, 0, 0, 0, 0, 0, 0, 0, 0, 0, 0, 0, 0, 0, 0, 0, 0, 0, 0, 0, 0, 0, 0, 0, 0, 0, 0, 0, 0, 0, 0, 0, 0, 0, 0, 0, 0, 0, 0, 0, 0, 0], "style": 0, "bounding_box": [139, 10, 622, 136], "category_id": 1, "occlusion": 1, "category_name": "short sleeve top"}, "source": "shop", "pair_id": 4648, "item1": {"segmentation": [[543, 76, 357, 105, 199, 97, 156, 311, 118, 567, 341, 602, 297, 377, 351, 604, 662, 580, 607, 300, 543, 76], [357, 105, 199, 97, 156, 311, 118, 567, 341, 602, 297, 377, 357, 105], [543, 76, 357, 105, 297, 377, 351, 604, 662, 580, 607, 300, 543, 76]], "scale": 3, "viewpoint": 3, "zoom_in": 1, "landmarks": [199, 97, 1, 357, 105, 2, 543, 76, 1, 156, 311, 2, 118, 567, 2, 341, 602, 2, 297, 377, 2, 351, 604, 2, 662, 580, 2, 607, 300, 2], "style": 2, "bounding_box": [97, 58, 669, 625], "category_id": 7, "occlusion": 1, "category_name": "shorts"}}