{"source": "user", "pair_id": 4718, "item1": {"segmentation": [[180, 90, 219, 139, 295, 175, 342, 142, 341, 95, 377, 109, 432, 317, 428, 415, 429, 467, 92, 464, 107, 349, 143, 113, 180, 90]], "scale": 3, "viewpoint": 2, "zoom_in": 2, "landmarks": [295, 167, 1, 180, 90, 2, 219, 139, 2, 295, 175, 2, 342, 142, 2, 341, 95, 2, 143, 113, 2, 107, 349, 2, 0, 0, 0, 0, 0, 0, 0, 0, 0, 0, 0, 0, 0, 0, 0, 0, 0, 0, 0, 0, 0, 0, 0, 0, 428, 415, 2, 432, 317, 2, 377, 109, 2], "style": 2, "bounding_box": [93, 86, 437, 467], "category_id": 12, "occlusion": 1, "category_name": "vest dress"}}