{"source": "user", "pair_id": 4924, "item1": {"segmentation": [[81, 2, 139, 25, 191, 5, 240, 2, 233, 99, 223, 168, 225, 236, 262, 367, 285, 484, 160, 524, 8, 506, 29, 377, 27, 224, 32, 151, 29, 75, 37, 2, 81, 2]], "scale": 3, "viewpoint": 2, "zoom_in": 2, "landmarks": [139, 5, 1, 0, 0, 0, 0, 0, 0, 139, 25, 2, 0, 0, 0, 0, 0, 0, 0, 0, 0, 29, 75, 2, 32, 151, 2, 27, 224, 2, 29, 377, 2, 8, 506, 2, 160, 524, 2, 0, 0, 0, 262, 367, 2, 225, 236, 2, 223, 168, 2, 233, 99, 2, 0, 0, 0], "style": 1, "bounding_box": [4, 0, 286, 553], "category_id": 12, "occlusion": 1, "category_name": "vest dress"}}