{"item2": {"segmentation": [[215, 652, 335, 676, 448, 653, 491, 815, 514, 958, 328, 957, 138, 957, 159, 797, 215, 652]], "scale": 2, "viewpoint": 2, "zoom_in": 3, "landmarks": [215, 652, 1, 335, 676, 1, 448, 653, 1, 159, 797, 2, 0, 0, 0, 0, 0, 0, 0, 0, 0, 491, 815, 2], "style": 0, "bounding_box": [122, 631, 522, 958], "category_id": 9, "occlusion": 2, "category_name": "skirt"}, "source": "shop", "pair_id": 4941, "item1": {"segmentation": [[248, 295, 280, 340, 336, 363, 372, 345, 383, 316, 406, 329, 419, 432, 449, 557, 469, 692, 343, 770, 211, 684, 220, 560, 227, 423, 212, 300, 248, 295]], "scale": 2, "viewpoint": 2, "zoom_in": 1, "landmarks": [320, 310, 1, 248, 295, 1, 280, 340, 1, 336, 363, 2, 372, 345, 2, 383, 316, 2, 212, 300, 2, 227, 423, 1, 220, 560, 2, 0, 0, 0, 0, 0, 0, 0, 0, 0, 449, 557, 2, 419, 432, 2, 406, 329, 2], "style": 1, "bounding_box": [173, 279, 477, 781], "category_id": 5, "occlusion": 2, "category_name": "vest"}}