{"item2": {"segmentation": [[77, 82, 172, 47, 247, 3, 349, 108, 407, 257, 291, 316, 264, 290, 259, 301, 195, 320, 131, 203, 77, 82], [172, 47, 247, 3, 349, 108, 407, 257, 291, 316, 264, 290, 172, 47], [77, 82, 172, 47, 264, 290, 259, 301, 195, 320, 131, 203, 77, 82]], "scale": 2, "viewpoint": 3, "zoom_in": 2, "landmarks": [0, 0, 0, 172, 47, 1, 77, 82, 1, 349, 108, 2, 407, 257, 2, 291, 316, 2, 264, 290, 2, 259, 301, 2, 195, 320, 2, 131, 203, 2], "style": 1, "bounding_box": [73, 0, 412, 331], "category_id": 7, "occlusion": 1, "category_name": "shorts"}, "source": "shop", "pair_id": 5449, "item1": {"segmentation": [[239, 3, 219, 23, 183, 4, 188, 17, 118, 73, 33, 85, 4, 55, 3, 2, 239, 3], [239, 3, 219, 23, 183, 4, 239, 3], [239, 3, 219, 23, 183, 4, 239, 3]], "scale": 1, "viewpoint": 2, "zoom_in": 3, "landmarks": [0, 0, 0, 0, 0, 0, 0, 0, 0, 0, 0, 0, 0, 0, 0, 0, 0, 0, 0, 0, 0, 0, 0, 0, 0, 0, 0, 0, 0, 0, 0, 0, 0, 219, 23, 2, 0, 0, 0, 0, 0, 0, 0, 0, 0, 0, 0, 0, 0, 0, 0, 0, 0, 0, 0, 0, 0, 0, 0, 0, 0, 0, 0, 0, 0, 0, 0, 0, 0, 0, 0, 0, 0, 0, 0, 0, 0, 0, 0, 0, 0, 0, 0, 0, 0, 0, 0, 0, 0, 0, 0, 0, 0, 0, 0, 0, 0, 0, 0], "style": 0, "bounding_box": [0, 0, 259, 89], "category_id": 2, "occlusion": 1, "category_name": "long sleeve top"}}