{"item2": {"segmentation": [[130, 164, 171, 173, 197, 160, 196, 227, 189, 295, 143, 341, 91, 307, 106, 228, 130, 164]], "scale": 2, "viewpoint": 2, "zoom_in": 1, "landmarks": [130, 164, 2, 171, 173, 2, 197, 160, 2, 106, 228, 2, 91, 307, 2, 143, 341, 2, 189, 295, 2, 196, 227, 2], "style": 3, "bounding_box": [83, 155, 207, 351], "category_id": 9, "occlusion": 1, "category_name": "skirt"}, "source": "user", "pair_id": 5740, "item1": {"segmentation": [[138, 31, 149, 39, 163, 40, 176, 39, 178, 27, 207, 41, 211, 87, 205, 127, 200, 159, 172, 172, 132, 166, 124, 139, 121, 112, 108, 45, 138, 31]], "scale": 2, "viewpoint": 2, "zoom_in": 1, "landmarks": [156, 28, 1, 138, 31, 1, 149, 39, 1, 163, 40, 1, 176, 39, 1, 178, 27, 1, 108, 45, 2, 121, 112, 1, 124, 139, 2, 0, 0, 0, 0, 0, 0, 0, 0, 0, 205, 127, 2, 211, 87, 2, 207, 41, 1], "style": 1, "bounding_box": [102, 25, 213, 176], "category_id": 5, "occlusion": 3, "category_name": "vest"}}