{"source": "user", "pair_id": 5806, "item1": {"segmentation": [[128, 45, 146, 84, 177, 109, 215, 91, 223, 54, 224, 163, 223, 202, 207, 242, 223, 311, 224, 398, 106, 399, 1, 398, 0, 274, 64, 210, 68, 174, 64, 141, 93, 46, 128, 45]], "scale": 3, "viewpoint": 2, "zoom_in": 3, "landmarks": [173, 77, 1, 128, 45, 2, 146, 84, 2, 177, 109, 2, 215, 91, 2, 0, 0, 0, 93, 46, 1, 64, 141, 2, 68, 174, 2, 64, 210, 2, 0, 0, 0, 0, 0, 0, 0, 0, 0, 0, 0, 0, 0, 0, 0, 207, 242, 2, 0, 0, 0, 0, 0, 0, 0, 0, 0], "style": 1, "bounding_box": [0, 42, 224, 399], "category_id": 12, "occlusion": 1, "category_name": "vest dress"}}