{"source": "user", "pair_id": 5977, "item1": {"segmentation": [[350, 3, 120, 2, 3, 3, 3, 630, 94, 503, 198, 373, 226, 334, 246, 388, 264, 458, 465, 410, 423, 240, 383, 70, 350, 3], [226, 334, 246, 388, 264, 458, 465, 410, 423, 240, 383, 70, 226, 334], [229, 2, 120, 2, 350, 3, 229, 2]], "scale": 3, "viewpoint": 1, "zoom_in": 3, "landmarks": [0, 0, 0, 0, 0, 0, 0, 0, 0, 0, 0, 0, 0, 0, 0, 0, 0, 0, 0, 0, 0, 0, 0, 0, 0, 0, 0, 0, 0, 0, 0, 0, 0, 0, 0, 0, 0, 0, 0, 0, 0, 0, 0, 0, 0, 0, 0, 0, 0, 0, 0, 94, 503, 2, 198, 373, 2, 226, 334, 2, 246, 388, 2, 264, 458, 2, 465, 410, 2, 423, 240, 2, 383, 70, 2], "style": 2, "bounding_box": [0, 0, 465, 630], "category_id": 1, "occlusion": 1, "category_name": "short sleeve top"}}