{"source": "user", "pair_id": 6805, "item1": {"segmentation": [[375, 1, 235, 0, 67, 31, 50, 159, 47, 285, 240, 289, 244, 248, 260, 280, 475, 144, 440, 55, 375, 1], [235, 0, 67, 31, 50, 159, 47, 285, 240, 289, 244, 248, 235, 0], [375, 1, 235, 0, 244, 248, 260, 280, 475, 144, 440, 55, 375, 1]], "scale": 3, "viewpoint": 1, "zoom_in": 2, "landmarks": [67, 31, 2, 0, 0, 0, 0, 0, 0, 50, 159, 2, 47, 285, 2, 0, 0, 0, 244, 248, 2, 260, 280, 2, 475, 144, 2, 440, 55, 2], "style": 1, "bounding_box": [44, 1, 478, 290], "category_id": 7, "occlusion": 1, "category_name": "shorts"}}