{"source": "user", "pair_id": 6924, "item1": {"segmentation": [[413, 6, 337, 99, 242, 198, 186, 91, 138, 3, 7, 7, 7, 351, 21, 436, 47, 503, 52, 640, 119, 804, 321, 828, 461, 675, 446, 594, 427, 507, 451, 489, 464, 461, 461, 1, 413, 6]], "scale": 3, "viewpoint": 2, "zoom_in": 3, "landmarks": [244, 18, 1, 0, 0, 0, 186, 91, 2, 242, 198, 2, 337, 99, 2, 0, 0, 0, 0, 0, 0, 0, 0, 0, 0, 0, 0, 0, 0, 0, 0, 0, 0, 0, 0, 0, 0, 0, 0, 21, 436, 2, 47, 503, 2, 52, 640, 2, 119, 804, 2, 0, 0, 0, 461, 675, 2, 446, 594, 2, 427, 507, 2, 451, 489, 2, 0, 0, 0, 0, 0, 0, 0, 0, 0, 0, 0, 0, 0, 0, 0, 0, 0, 0, 0, 0, 0], "style": 1, "bounding_box": [0, 0, 466, 830], "category_id": 10, "occlusion": 1, "category_name": "short sleeve dress"}}