{"source": "user", "pair_id": 6995, "item1": {"segmentation": [[269, 7, 227, 1, 71, 12, 36, 102, 5, 207, 120, 258, 127, 199, 130, 151, 131, 187, 112, 362, 127, 536, 271, 603, 465, 590, 463, 1, 269, 7], [71, 12, 36, 102, 5, 207, 120, 258, 127, 199, 130, 151, 71, 12]], "scale": 3, "viewpoint": 2, "zoom_in": 2, "landmarks": [0, 0, 0, 0, 0, 0, 0, 0, 0, 269, 7, 2, 0, 0, 0, 0, 0, 0, 71, 12, 2, 36, 102, 2, 5, 207, 2, 120, 258, 2, 127, 199, 1, 130, 151, 2, 131, 187, 2, 112, 362, 2, 0, 0, 0, 0, 0, 0, 0, 0, 0, 0, 0, 0, 0, 0, 0, 0, 0, 0, 0, 0, 0, 0, 0, 0, 0, 0, 0, 0, 0, 0, 0, 0, 0], "style": 1, "bounding_box": [0, 0, 465, 621], "category_id": 1, "occlusion": 1, "category_name": "short sleeve top"}}