{"item2": {"segmentation": [[82, 1, 88, 101, 80, 180, 293, 187, 533, 250, 498, 119, 475, 2, 414, 5, 401, 60, 638, 6, 82, 1], [414, 5, 401, 60, 638, 6, 414, 5]], "scale": 2, "viewpoint": 2, "zoom_in": 3, "landmarks": [0, 0, 0, 0, 0, 0, 0, 0, 0, 0, 0, 0, 0, 0, 0, 0, 0, 0, 0, 0, 0, 0, 0, 0, 0, 0, 0, 0, 0, 0, 0, 0, 0, 0, 0, 0, 0, 0, 0, 88, 101, 2, 0, 0, 0, 0, 0, 0, 0, 0, 0, 498, 119, 1, 0, 0, 0, 0, 0, 0, 0, 0, 0, 401, 60, 2, 0, 0, 0, 0, 0, 0, 0, 0, 0], "style": 0, "bounding_box": [71, 0, 639, 254], "category_id": 1, "occlusion": 1, "category_name": "short sleeve top"}, "source": "shop", "pair_id": 7810, "item1": {"segmentation": [[140, 182, 296, 173, 473, 179, 467, 469, 470, 722, 225, 705, 49, 610, 114, 394, 140, 182]], "scale": 3, "viewpoint": 2, "zoom_in": 1, "landmarks": [140, 182, 2, 296, 173, 1, 473, 179, 1, 114, 394, 2, 49, 610, 2, 225, 705, 2, 470, 722, 2, 467, 469, 2], "style": 1, "bounding_box": [38, 152, 488, 754], "category_id": 9, "occlusion": 2, "category_name": "skirt"}}