{"item2": {"segmentation": [[326, 2, 333, 71, 376, 69, 409, 70, 425, 3, 359, 3, 373, 55, 354, 75, 332, 95, 350, 118, 387, 99, 420, 68, 411, 3, 326, 2], [359, 3, 373, 55, 354, 75, 332, 95, 350, 118, 387, 99, 420, 68, 411, 3, 359, 3], [373, 55, 354, 75, 332, 95, 350, 118, 387, 99, 420, 68, 373, 55]], "scale": 1, "viewpoint": 2, "zoom_in": 3, "landmarks": [0, 0, 0, 0, 0, 0, 0, 0, 0, 0, 0, 0, 0, 0, 0, 0, 0, 0, 0, 0, 0, 0, 0, 0, 0, 0, 0, 0, 0, 0, 0, 0, 0, 0, 0, 0, 0, 0, 0, 0, 0, 0, 0, 0, 0, 0, 0, 0, 0, 0, 0, 0, 0, 0, 0, 0, 0, 0, 0, 0, 0, 0, 0, 0, 0, 0, 0, 0, 0, 0, 0, 0, 0, 0, 0, 373, 55, 2, 354, 75, 2, 332, 95, 2, 350, 118, 2, 387, 99, 2, 420, 68, 2, 0, 0, 0, 0, 0, 0], "style": 0, "bounding_box": [317, 0, 427, 128], "category_id": 2, "occlusion": 1, "category_name": "long sleeve top"}, "source": "shop", "pair_id": 8028, "item1": {"segmentation": [[405, 72, 369, 75, 332, 78, 332, 165, 324, 234, 391, 237, 440, 213, 431, 150, 405, 72]], "scale": 1, "viewpoint": 3, "zoom_in": 1, "landmarks": [405, 72, 1, 369, 75, 1, 332, 78, 1, 431, 150, 2, 440, 213, 2, 391, 237, 2, 324, 234, 2, 332, 165, 2], "style": 1, "bounding_box": [320, 68, 440, 245], "category_id": 9, "occlusion": 2, "category_name": "skirt"}}