{"source": "user", "pair_id": 9084, "item1": {"segmentation": [[189, 2, 204, 89, 256, 159, 335, 81, 363, 1, 466, 2, 466, 259, 448, 303, 432, 345, 373, 494, 304, 617, 210, 567, 144, 483, 96, 381, 72, 248, 55, 180, 45, 120, 2, 3, 189, 2]], "scale": 3, "viewpoint": 2, "zoom_in": 3, "landmarks": [266, 24, 1, 0, 0, 0, 204, 89, 2, 256, 159, 2, 335, 81, 2, 0, 0, 0, 0, 0, 0, 45, 120, 2, 55, 180, 2, 72, 248, 2, 96, 381, 2, 144, 483, 2, 210, 567, 2, 0, 0, 0, 373, 494, 2, 432, 345, 2, 448, 303, 2, 0, 0, 0, 0, 0, 0], "style": 1, "bounding_box": [0, 0, 467, 623], "category_id": 12, "occlusion": 1, "category_name": "vest dress"}}