{"source": "user", "pair_id": 9444, "item1": {"segmentation": [[337, 3, 176, 3, 5, 6, 4, 352, 32, 663, 164, 630, 196, 216, 253, 500, 391, 441, 370, 197, 337, 3], [176, 3, 5, 6, 4, 352, 32, 663, 164, 630, 196, 216, 176, 3], [337, 3, 176, 3, 196, 216, 253, 500, 391, 441, 370, 197, 337, 3]], "scale": 3, "viewpoint": 2, "zoom_in": 3, "landmarks": [0, 0, 0, 0, 0, 0, 0, 0, 0, 0, 0, 0, 32, 663, 2, 164, 630, 2, 196, 216, 2, 253, 500, 2, 391, 441, 2, 370, 197, 2], "style": 1, "bounding_box": [0, 0, 403, 703], "category_id": 7, "occlusion": 1, "category_name": "shorts"}}