{"source": "user", "pair_id": 9521, "item1": {"segmentation": [[350, 97, 302, 132, 238, 150, 178, 144, 141, 115, 83, 115, 1, 137, 3, 649, 244, 627, 466, 630, 466, 129, 437, 118, 350, 97], [238, 116, 141, 115, 178, 144, 238, 150, 302, 132, 350, 97, 238, 116]], "scale": 3, "viewpoint": 1, "zoom_in": 3, "landmarks": [238, 116, 2, 141, 115, 2, 178, 144, 2, 238, 150, 2, 302, 132, 2, 350, 97, 2, 83, 115, 2, 0, 0, 0, 0, 0, 0, 0, 0, 0, 0, 0, 0, 0, 0, 0, 0, 0, 0, 0, 0, 0, 0, 0, 0, 244, 627, 2, 0, 0, 0, 0, 0, 0, 0, 0, 0, 0, 0, 0, 0, 0, 0, 0, 0, 0, 0, 0, 0, 0, 0, 0, 437, 118, 2], "style": 1, "bounding_box": [0, 90, 466, 655], "category_id": 1, "occlusion": 1, "category_name": "short sleeve top"}}