{"item2": {"segmentation": [[306, 30, 215, 31, 100, 31, 90, 148, 85, 259, 239, 235, 245, 159, 239, 253, 358, 216, 339, 114, 306, 30], [215, 31, 100, 31, 90, 148, 85, 259, 239, 235, 245, 159, 215, 31], [306, 30, 215, 31, 245, 159, 239, 253, 358, 216, 339, 114, 306, 30]], "scale": 2, "viewpoint": 2, "zoom_in": 1, "landmarks": [100, 31, 1, 215, 31, 1, 306, 30, 1, 90, 148, 2, 85, 259, 2, 239, 235, 2, 245, 159, 2, 239, 253, 2, 358, 216, 2, 339, 114, 2], "style": 6, "bounding_box": [79, 30, 359, 266], "category_id": 7, "occlusion": 2, "category_name": "shorts"}, "source": "shop", "pair_id": 9949, "item1": {"segmentation": [[296, 1, 313, 48, 221, 60, 95, 42, 92, 1, 296, 1]], "scale": 1, "viewpoint": 2, "zoom_in": 3, "landmarks": [0, 0, 0, 0, 0, 0, 0, 0, 0, 0, 0, 0, 0, 0, 0, 0, 0, 0, 0, 0, 0, 0, 0, 0, 0, 0, 0, 95, 42, 1, 221, 60, 2, 313, 48, 2, 0, 0, 0, 0, 0, 0, 0, 0, 0], "style": 0, "bounding_box": [91, 0, 315, 61], "category_id": 5, "occlusion": 1, "category_name": "vest"}}