{"item2": {"segmentation": [[235, 3, 238, 145, 372, 159, 457, 177, 448, 3, 235, 3]], "scale": 1, "viewpoint": 2, "zoom_in": 3, "landmarks": [0, 0, 0, 0, 0, 0, 0, 0, 0, 0, 0, 0, 0, 0, 0, 0, 0, 0, 0, 0, 0, 0, 0, 0, 0, 0, 0, 0, 0, 0, 0, 0, 0, 0, 0, 0, 0, 0, 0, 0, 0, 0, 238, 145, 1, 372, 159, 2, 457, 177, 2, 0, 0, 0, 0, 0, 0, 0, 0, 0, 0, 0, 0, 0, 0, 0, 0, 0, 0, 0, 0, 0, 0, 0, 0], "style": 0, "bounding_box": [222, 0, 460, 178], "category_id": 1, "occlusion": 1, "category_name": "short sleeve top"}, "source": "shop", "pair_id": 9982, "item1": {"segmentation": [[460, 143, 376, 142, 241, 129, 226, 317, 224, 499, 337, 513, 372, 320, 354, 490, 466, 504, 475, 330, 460, 143], [376, 142, 241, 129, 226, 317, 224, 499, 337, 513, 372, 320, 376, 142], [460, 143, 376, 142, 372, 320, 354, 490, 466, 504, 475, 330, 460, 143]], "scale": 2, "viewpoint": 2, "zoom_in": 1, "landmarks": [241, 129, 1, 376, 142, 1, 460, 143, 1, 226, 317, 2, 224, 499, 2, 337, 513, 2, 372, 320, 2, 354, 490, 2, 466, 504, 2, 475, 330, 2], "style": 1, "bounding_box": [219, 126, 489, 516], "category_id": 7, "occlusion": 2, "category_name": "shorts"}}