{"item2": {"segmentation": [[409, 261, 383, 259, 358, 252, 317, 359, 308, 455, 383, 471, 457, 462, 443, 354, 409, 261]], "scale": 2, "viewpoint": 3, "zoom_in": 1, "landmarks": [409, 261, 1, 383, 259, 1, 358, 252, 1, 443, 354, 2, 457, 462, 2, 383, 471, 2, 308, 455, 2, 317, 359, 2], "style": 2, "bounding_box": [298, 250, 461, 481], "category_id": 9, "occlusion": 2, "category_name": "skirt"}, "source": "shop", "pair_id": 10039, "item1": {"segmentation": [[434, 163, 407, 153, 388, 152, 361, 188, 341, 218, 334, 245, 394, 268, 441, 266, 438, 239, 439, 215, 441, 171, 434, 163]], "scale": 1, "viewpoint": 3, "zoom_in": 1, "landmarks": [432, 212, 2, 434, 163, 1, 0, 0, 0, 0, 0, 0, 0, 0, 0, 407, 153, 2, 441, 171, 1, 439, 215, 2, 438, 239, 2, 441, 266, 2, 394, 268, 1, 334, 245, 2, 341, 218, 2, 361, 188, 2, 388, 152, 2], "style": 1, "bounding_box": [327, 145, 446, 278], "category_id": 5, "occlusion": 2, "category_name": "vest"}}