{"item2": {"segmentation": [[454, 521, 540, 477, 594, 418, 677, 467, 697, 587, 621, 589, 467, 589, 454, 521]], "scale": 2, "viewpoint": 2, "zoom_in": 2, "landmarks": [454, 521, 2, 540, 477, 2, 594, 418, 2, 467, 589, 2, 0, 0, 0, 0, 0, 0, 0, 0, 0, 677, 467, 2], "style": 0, "bounding_box": [444, 414, 701, 590], "category_id": 9, "occlusion": 1, "category_name": "skirt"}, "source": "shop", "pair_id": 10146, "item1": {"segmentation": [[317, 271, 382, 313, 459, 329, 455, 260, 423, 219, 448, 216, 522, 291, 556, 355, 590, 420, 542, 473, 448, 520, 406, 478, 355, 423, 295, 293, 317, 271]], "scale": 2, "viewpoint": 2, "zoom_in": 1, "landmarks": [376, 231, 1, 317, 271, 2, 382, 313, 2, 459, 329, 2, 455, 260, 2, 423, 219, 2, 295, 293, 2, 355, 423, 2, 406, 478, 2, 0, 0, 0, 0, 0, 0, 0, 0, 0, 556, 355, 2, 522, 291, 2, 448, 216, 2], "style": 1, "bounding_box": [290, 213, 595, 522], "category_id": 5, "occlusion": 1, "category_name": "vest"}}