{"item2": {"segmentation": [[511, 104, 384, 109, 246, 103, 227, 309, 246, 524, 370, 518, 382, 311, 370, 520, 481, 538, 514, 318, 511, 104], [384, 109, 246, 103, 227, 309, 246, 524, 370, 518, 382, 311, 384, 109], [511, 104, 384, 109, 382, 311, 370, 520, 481, 538, 514, 318, 511, 104]], "scale": 2, "viewpoint": 2, "zoom_in": 1, "landmarks": [246, 103, 1, 384, 109, 1, 511, 104, 1, 227, 309, 2, 246, 524, 2, 370, 518, 2, 382, 311, 2, 370, 520, 1, 481, 538, 2, 514, 318, 2], "style": 7, "bounding_box": [198, 76, 558, 618], "category_id": 7, "occlusion": 2, "category_name": "shorts"}, "source": "shop", "pair_id": 10206, "item1": {"segmentation": [[253, 4, 239, 152, 379, 211, 518, 152, 498, 3, 253, 4]], "scale": 2, "viewpoint": 2, "zoom_in": 3, "landmarks": [0, 0, 0, 0, 0, 0, 0, 0, 0, 0, 0, 0, 0, 0, 0, 0, 0, 0, 0, 0, 0, 0, 0, 0, 0, 0, 0, 0, 0, 0, 0, 0, 0, 0, 0, 0, 0, 0, 0, 0, 0, 0, 239, 152, 2, 379, 211, 2, 518, 152, 2, 0, 0, 0, 0, 0, 0, 0, 0, 0, 0, 0, 0, 0, 0, 0, 0, 0, 0, 0, 0, 0, 0, 0, 0], "style": 0, "bounding_box": [181, 0, 565, 240], "category_id": 1, "occlusion": 1, "category_name": "short sleeve top"}}