{"item2": {"segmentation": [[110, 2, 78, 104, 73, 256, 244, 172, 408, 291, 406, 134, 402, 4, 110, 2]], "scale": 2, "viewpoint": 2, "zoom_in": 2, "landmarks": [0, 0, 0, 0, 0, 0, 0, 0, 0, 0, 0, 0, 0, 0, 0, 0, 0, 0, 0, 0, 0, 0, 0, 0, 0, 0, 0, 0, 0, 0, 0, 0, 0, 0, 0, 0, 0, 0, 0, 78, 104, 2, 73, 256, 2, 0, 0, 0, 408, 291, 2, 406, 134, 2, 0, 0, 0, 0, 0, 0, 0, 0, 0, 0, 0, 0, 0, 0, 0, 0, 0, 0, 0, 0, 0], "style": 0, "bounding_box": [7, 2, 433, 308], "category_id": 1, "occlusion": 1, "category_name": "short sleeve top"}, "source": "shop", "pair_id": 10407, "item1": {"segmentation": [[377, 148, 235, 156, 108, 143, 70, 285, 53, 441, 213, 496, 222, 458, 229, 497, 405, 462, 402, 311, 377, 148], [235, 156, 108, 143, 70, 285, 53, 441, 213, 496, 222, 458, 235, 156], [377, 148, 235, 156, 222, 458, 229, 497, 405, 462, 402, 311, 377, 148]], "scale": 3, "viewpoint": 2, "zoom_in": 1, "landmarks": [108, 143, 1, 235, 156, 1, 377, 148, 1, 70, 285, 2, 53, 441, 2, 213, 496, 2, 222, 458, 2, 229, 497, 2, 405, 462, 2, 402, 311, 2], "style": 1, "bounding_box": [39, 135, 428, 511], "category_id": 7, "occlusion": 2, "category_name": "shorts"}}