{"item2": {"segmentation": [[490, 432, 456, 438, 408, 441, 389, 512, 377, 576, 452, 585, 519, 567, 512, 503, 490, 432]], "scale": 1, "viewpoint": 3, "zoom_in": 1, "landmarks": [490, 432, 1, 456, 438, 1, 408, 441, 1, 512, 503, 2, 519, 567, 2, 452, 585, 2, 377, 576, 2, 389, 512, 2], "style": 2, "bounding_box": [373, 428, 520, 589], "category_id": 9, "occlusion": 2, "category_name": "skirt"}, "source": "shop", "pair_id": 10501, "item1": {"segmentation": [[474, 301, 430, 307, 388, 344, 396, 373, 404, 407, 406, 442, 457, 438, 504, 430, 512, 402, 518, 376, 510, 331, 474, 301]], "scale": 1, "viewpoint": 3, "zoom_in": 1, "landmarks": [457, 299, 1, 474, 301, 1, 0, 0, 0, 0, 0, 0, 0, 0, 0, 430, 307, 2, 510, 331, 2, 518, 376, 2, 512, 402, 2, 0, 0, 0, 0, 0, 0, 0, 0, 0, 404, 407, 2, 396, 373, 2, 388, 344, 2], "style": 1, "bounding_box": [385, 296, 519, 446], "category_id": 5, "occlusion": 1, "category_name": "vest"}}