{"item2": {"segmentation": [[121, 1, 131, 45, 233, 57, 318, 54, 321, 1, 121, 1]], "scale": 1, "viewpoint": 2, "zoom_in": 3, "landmarks": [0, 0, 0, 0, 0, 0, 0, 0, 0, 0, 0, 0, 0, 0, 0, 0, 0, 0, 0, 0, 0, 0, 0, 0, 0, 0, 0, 0, 0, 0, 0, 0, 0, 0, 0, 0, 0, 0, 0, 0, 0, 0, 0, 0, 0, 0, 0, 0, 0, 0, 0, 0, 0, 0, 0, 0, 0, 0, 0, 0, 0, 0, 0, 0, 0, 0, 0, 0, 0, 0, 0, 0, 0, 0, 0], "style": 0, "bounding_box": [117, 0, 332, 66], "category_id": 1, "occlusion": 1, "category_name": "short sleeve top"}, "source": "shop", "pair_id": 11328, "item1": {"segmentation": [[304, 51, 230, 58, 140, 46, 122, 149, 109, 237, 225, 261, 229, 234, 227, 259, 334, 232, 327, 141, 304, 51], [230, 58, 140, 46, 122, 149, 109, 237, 225, 261, 229, 234, 230, 58], [304, 51, 230, 58, 229, 234, 227, 259, 334, 232, 327, 141, 304, 51]], "scale": 2, "viewpoint": 2, "zoom_in": 1, "landmarks": [140, 46, 1, 230, 58, 2, 304, 51, 2, 122, 149, 2, 109, 237, 2, 225, 261, 2, 229, 234, 2, 227, 259, 2, 334, 232, 2, 327, 141, 2], "style": 2, "bounding_box": [106, 45, 340, 267], "category_id": 7, "occlusion": 1, "category_name": "shorts"}}