{"item2": {"segmentation": [[229, 575, 336, 564, 420, 530, 535, 646, 629, 789, 438, 880, 230, 916, 218, 738, 229, 575]], "scale": 2, "viewpoint": 2, "zoom_in": 1, "landmarks": [229, 575, 2, 336, 564, 1, 420, 530, 1, 218, 738, 2, 230, 916, 2, 438, 880, 2, 629, 789, 2, 535, 646, 2], "style": 2, "bounding_box": [206, 519, 631, 933], "category_id": 9, "occlusion": 2, "category_name": "skirt"}, "source": "shop", "pair_id": 11540, "item1": {"segmentation": [[170, 282, 212, 312, 283, 328, 320, 297, 332, 254, 409, 269, 403, 392, 413, 456, 423, 527, 329, 565, 225, 577, 206, 498, 179, 428, 97, 319, 170, 282]], "scale": 2, "viewpoint": 2, "zoom_in": 1, "landmarks": [257, 273, 1, 170, 282, 1, 212, 312, 1, 283, 328, 2, 320, 297, 2, 332, 254, 2, 97, 319, 2, 179, 428, 2, 206, 498, 1, 0, 0, 0, 0, 0, 0, 0, 0, 0, 413, 456, 1, 403, 392, 2, 409, 269, 1], "style": 1, "bounding_box": [89, 246, 461, 583], "category_id": 5, "occlusion": 2, "category_name": "vest"}}