{"source": "user", "pair_id": 12237, "item1": {"segmentation": [[349, 99, 316, 137, 254, 144, 183, 124, 160, 75, 34, 93, 2, 96, 3, 598, 245, 606, 465, 601, 467, 139, 430, 132, 349, 99], [257, 114, 160, 75, 183, 124, 254, 144, 316, 137, 349, 99, 257, 114]], "scale": 3, "viewpoint": 1, "zoom_in": 3, "landmarks": [257, 114, 2, 160, 75, 2, 183, 124, 2, 254, 144, 2, 316, 137, 2, 349, 99, 2, 34, 93, 2, 0, 0, 0, 0, 0, 0, 0, 0, 0, 0, 0, 0, 0, 0, 0, 0, 0, 0, 0, 0, 0, 0, 0, 0, 245, 606, 2, 0, 0, 0, 0, 0, 0, 0, 0, 0, 0, 0, 0, 0, 0, 0, 0, 0, 0, 0, 0, 0, 0, 0, 0, 430, 132, 2], "style": 1, "bounding_box": [0, 65, 466, 612], "category_id": 1, "occlusion": 1, "category_name": "short sleeve top"}}