{"item2": {"segmentation": [[324, 47, 241, 60, 147, 52, 132, 157, 147, 258, 260, 270, 267, 203, 273, 249, 365, 219, 351, 137, 324, 47], [241, 60, 147, 52, 132, 157, 147, 258, 260, 270, 267, 203, 241, 60], [324, 47, 241, 60, 267, 203, 273, 249, 365, 219, 351, 137, 324, 47]], "scale": 2, "viewpoint": 2, "zoom_in": 1, "landmarks": [147, 52, 1, 241, 60, 1, 324, 47, 1, 132, 157, 2, 147, 258, 1, 260, 270, 2, 267, 203, 2, 273, 249, 2, 365, 219, 2, 351, 137, 2], "style": 0, "bounding_box": [127, 39, 375, 285], "category_id": 7, "occlusion": 2, "category_name": "shorts"}, "source": "shop", "pair_id": 12633, "item1": {"segmentation": [[131, 2, 144, 75, 234, 67, 324, 50, 330, 2, 131, 2]], "scale": 1, "viewpoint": 2, "zoom_in": 3, "landmarks": [0, 0, 0, 0, 0, 0, 0, 0, 0, 0, 0, 0, 0, 0, 0, 0, 0, 0, 0, 0, 0, 0, 0, 0, 0, 0, 0, 0, 0, 0, 0, 0, 0, 0, 0, 0, 0, 0, 0, 0, 0, 0, 0, 0, 0, 0, 0, 0, 0, 0, 0, 0, 0, 0, 0, 0, 0, 0, 0, 0, 0, 0, 0, 0, 0, 0, 0, 0, 0, 0, 0, 0, 0, 0, 0], "style": 1, "bounding_box": [125, 0, 344, 86], "category_id": 1, "occlusion": 1, "category_name": "short sleeve top"}}