{"item2": {"segmentation": [[261, 72, 207, 75, 148, 87, 116, 209, 90, 350, 85, 424, 206, 441, 201, 366, 169, 219, 159, 395, 160, 472, 308, 448, 300, 379, 295, 220, 261, 72], [207, 75, 148, 87, 116, 209, 90, 350, 85, 424, 206, 441, 201, 366, 169, 219, 207, 75], [261, 72, 207, 75, 169, 219, 159, 395, 160, 472, 308, 448, 300, 379, 295, 220, 261, 72]], "scale": 2, "viewpoint": 3, "zoom_in": 1, "landmarks": [148, 87, 2, 207, 75, 1, 261, 72, 1, 116, 209, 2, 90, 350, 2, 85, 424, 2, 206, 441, 1, 201, 366, 1, 169, 219, 1, 159, 395, 2, 160, 472, 2, 308, 448, 2, 300, 379, 2, 295, 220, 1], "style": 2, "bounding_box": [71, 59, 326, 489], "category_id": 8, "occlusion": 2, "category_name": "trousers"}, "source": "shop", "pair_id": 12774, "item1": {"segmentation": [[141, 6, 146, 83, 206, 81, 264, 71, 263, 0, 141, 6]], "scale": 1, "viewpoint": 2, "zoom_in": 3, "landmarks": [0, 0, 0, 0, 0, 0, 0, 0, 0, 0, 0, 0, 0, 0, 0, 0, 0, 0, 0, 0, 0, 0, 0, 0, 0, 0, 0, 0, 0, 0, 0, 0, 0, 0, 0, 0, 0, 0, 0, 0, 0, 0, 0, 0, 0, 0, 0, 0, 0, 0, 0, 0, 0, 0, 0, 0, 0, 0, 0, 0, 0, 0, 0, 0, 0, 0, 0, 0, 0, 0, 0, 0, 0, 0, 0], "style": 1, "bounding_box": [128, 1, 298, 101], "category_id": 1, "occlusion": 1, "category_name": "short sleeve top"}}