{"source": "shop", "pair_id": 12878, "item1": {"segmentation": [[17, 1, 61, 355, 286, 443, 476, 391, 465, 7, 17, 1]], "scale": 3, "viewpoint": 2, "zoom_in": 3, "landmarks": [0, 0, 0, 0, 0, 0, 0, 0, 0, 0, 0, 0, 0, 0, 0, 0, 0, 0, 0, 0, 0, 0, 0, 0, 0, 0, 0, 0, 0, 0, 0, 0, 0, 0, 0, 0, 0, 0, 0, 0, 0, 0, 0, 0, 0, 0, 0, 0, 0, 0, 0, 0, 0, 0, 61, 355, 2, 286, 443, 2, 476, 391, 2, 0, 0, 0, 0, 0, 0, 0, 0, 0, 0, 0, 0, 0, 0, 0, 0, 0, 0, 0, 0, 0, 0, 0, 0, 0, 0, 0, 0, 0, 0, 0, 0, 0, 0, 0, 0], "style": 2, "bounding_box": [12, 1, 517, 480], "category_id": 2, "occlusion": 1, "category_name": "long sleeve top"}}