{"item2": {"segmentation": [[200, 17, 190, 44, 308, 77, 315, 57, 317, 37, 294, 36, 287, 77, 295, 135, 412, 123, 522, 147, 550, 93, 574, 59, 582, 43, 605, 37, 633, 43, 702, 19, 200, 17], [200, 17, 190, 44, 308, 77, 315, 57, 317, 37, 200, 17], [582, 43, 605, 37, 633, 43, 702, 19, 582, 43]], "scale": 1, "viewpoint": 2, "zoom_in": 2, "landmarks": [0, 0, 0, 0, 0, 0, 0, 0, 0, 0, 0, 0, 0, 0, 0, 0, 0, 0, 0, 0, 0, 0, 0, 0, 190, 44, 2, 308, 77, 1, 315, 57, 1, 317, 37, 1, 294, 36, 2, 287, 77, 2, 0, 0, 0, 0, 0, 0, 0, 0, 0, 550, 93, 2, 574, 59, 2, 582, 43, 2, 605, 37, 2, 633, 43, 2, 0, 0, 0, 0, 0, 0, 0, 0, 0], "style": 0, "bounding_box": [183, 0, 733, 170], "category_id": 1, "occlusion": 1, "category_name": "short sleeve top"}, "source": "shop", "pair_id": 13403, "item1": {"segmentation": [[294, 142, 404, 124, 517, 145, 545, 294, 555, 509, 386, 512, 236, 498, 258, 293, 294, 142]], "scale": 2, "viewpoint": 2, "zoom_in": 1, "landmarks": [294, 142, 2, 404, 124, 2, 517, 145, 1, 258, 293, 2, 236, 498, 2, 386, 512, 2, 555, 509, 2, 545, 294, 2], "style": 3, "bounding_box": [232, 121, 558, 523], "category_id": 9, "occlusion": 1, "category_name": "skirt"}}