{"item2": {"segmentation": [[296, 1, 272, 111, 461, 106, 630, 97, 651, 1, 296, 1]], "scale": 2, "viewpoint": 2, "zoom_in": 3, "landmarks": [0, 0, 0, 0, 0, 0, 0, 0, 0, 0, 0, 0, 0, 0, 0, 0, 0, 0, 0, 0, 0, 0, 0, 0, 0, 0, 0, 0, 0, 0, 0, 0, 0, 0, 0, 0, 0, 0, 0, 0, 0, 0, 272, 111, 2, 0, 0, 0, 0, 0, 0, 0, 0, 0, 0, 0, 0, 0, 0, 0, 0, 0, 0, 0, 0, 0, 0, 0, 0, 0, 0, 0, 0, 0, 0], "style": 0, "bounding_box": [266, 0, 659, 122], "category_id": 1, "occlusion": 1, "category_name": "short sleeve top"}, "source": "shop", "pair_id": 13704, "item1": {"segmentation": [[608, 92, 435, 97, 277, 94, 254, 213, 253, 322, 422, 375, 420, 346, 431, 376, 643, 369, 639, 243, 608, 92], [435, 97, 277, 94, 254, 213, 253, 322, 422, 375, 420, 346, 435, 97], [608, 92, 435, 97, 420, 346, 431, 376, 643, 369, 639, 243, 608, 92]], "scale": 3, "viewpoint": 2, "zoom_in": 1, "landmarks": [277, 94, 1, 435, 97, 1, 608, 92, 1, 254, 213, 2, 253, 322, 1, 422, 375, 2, 420, 346, 2, 431, 376, 2, 643, 369, 2, 639, 243, 2], "style": 1, "bounding_box": [236, 90, 655, 424], "category_id": 7, "occlusion": 2, "category_name": "shorts"}}