{"source": "user", "pair_id": 13795, "item1": {"segmentation": [[428, 14, 352, 149, 213, 197, 81, 159, 26, 27, 1, 51, 2, 539, 8, 777, 238, 762, 466, 756, 456, 537, 465, 315, 464, 22, 428, 14], [223, 71, 26, 27, 81, 159, 213, 197, 352, 149, 428, 14, 223, 71]], "scale": 3, "viewpoint": 1, "zoom_in": 3, "landmarks": [223, 71, 2, 26, 27, 2, 81, 159, 2, 213, 197, 2, 352, 149, 2, 428, 14, 2, 0, 0, 0, 0, 0, 0, 0, 0, 0, 0, 0, 0, 0, 0, 0, 0, 0, 0, 0, 0, 0, 0, 0, 0, 8, 777, 2, 238, 762, 2, 0, 0, 0, 456, 537, 2, 0, 0, 0, 0, 0, 0, 0, 0, 0, 0, 0, 0, 0, 0, 0, 0, 0, 0, 0, 0, 0], "style": 1, "bounding_box": [0, 4, 466, 798], "category_id": 1, "occlusion": 1, "category_name": "short sleeve top"}}