{"source": "user", "pair_id": 13996, "item1": {"segmentation": [[280, 45, 251, 82, 193, 110, 142, 69, 105, 13, 2, 28, 5, 714, 210, 719, 463, 731, 467, 489, 465, 340, 461, 254, 408, 110, 280, 45], [197, 35, 105, 13, 142, 69, 193, 110, 251, 82, 280, 45, 197, 35]], "scale": 3, "viewpoint": 1, "zoom_in": 3, "landmarks": [197, 35, 2, 105, 13, 2, 142, 69, 2, 193, 110, 2, 251, 82, 2, 280, 45, 2, 0, 0, 0, 0, 0, 0, 0, 0, 0, 0, 0, 0, 0, 0, 0, 0, 0, 0, 0, 0, 0, 0, 0, 0, 0, 0, 0, 0, 0, 0, 0, 0, 0, 0, 0, 0, 0, 0, 0, 210, 719, 2, 0, 0, 0, 0, 0, 0, 0, 0, 0, 0, 0, 0, 0, 0, 0, 0, 0, 0, 0, 0, 0, 0, 0, 0, 0, 0, 0, 0, 0, 0, 0, 0, 0, 0, 0, 0, 408, 110, 2], "style": 1, "bounding_box": [0, 0, 466, 815], "category_id": 2, "occlusion": 1, "category_name": "long sleeve top"}}