{"item2": {"segmentation": [[653, 195, 482, 142, 337, 4, 221, 133, 156, 247, 318, 360, 352, 332, 344, 369, 504, 453, 576, 338, 653, 195], [482, 142, 337, 4, 221, 133, 156, 247, 318, 360, 352, 332, 482, 142], [653, 195, 482, 142, 352, 332, 344, 369, 504, 453, 576, 338, 653, 195]], "scale": 3, "viewpoint": 2, "zoom_in": 2, "landmarks": [0, 0, 0, 482, 142, 1, 653, 195, 1, 221, 133, 2, 156, 247, 2, 318, 360, 2, 352, 332, 2, 344, 369, 2, 504, 453, 2, 576, 338, 2], "style": 1, "bounding_box": [146, 3, 673, 474], "category_id": 7, "occlusion": 1, "category_name": "shorts"}, "source": "shop", "pair_id": 14511, "item1": {"segmentation": [[274, 3, 279, 27, 471, 115, 654, 225, 684, 134, 696, 0, 274, 3]], "scale": 2, "viewpoint": 2, "zoom_in": 3, "landmarks": [0, 0, 0, 0, 0, 0, 0, 0, 0, 0, 0, 0, 0, 0, 0, 0, 0, 0, 0, 0, 0, 0, 0, 0, 0, 0, 0, 0, 0, 0, 0, 0, 0, 0, 0, 0, 0, 0, 0, 0, 0, 0, 279, 27, 2, 471, 115, 2, 654, 225, 2, 684, 134, 1, 0, 0, 0, 0, 0, 0, 0, 0, 0, 0, 0, 0, 0, 0, 0, 0, 0, 0, 0, 0, 0], "style": 0, "bounding_box": [263, 0, 698, 242], "category_id": 1, "occlusion": 1, "category_name": "short sleeve top"}}