{"source": "user", "pair_id": 14769, "item1": {"segmentation": [[113, 2, 139, 79, 202, 92, 264, 70, 282, 3, 314, 2, 391, 133, 396, 367, 431, 622, 7, 623, 43, 373, 44, 165, 83, 15, 113, 2], [189, 25, 113, 2, 139, 79, 202, 92, 264, 70, 282, 3, 189, 25]], "scale": 3, "viewpoint": 1, "zoom_in": 3, "landmarks": [189, 25, 2, 0, 0, 0, 139, 79, 2, 202, 92, 2, 264, 70, 2, 0, 0, 0, 83, 15, 2, 44, 165, 2, 43, 373, 2, 0, 0, 0, 0, 0, 0, 0, 0, 0, 396, 367, 2, 391, 133, 2, 0, 0, 0], "style": 2, "bounding_box": [5, 1, 435, 623], "category_id": 5, "occlusion": 1, "category_name": "vest"}}